analysis/__init__.py
analysis/dataset_definition_cases.py
analysis/dataset_definition_controls.py
analysis/write_matching_config.py
osmatching/__init__.py
osmatching/__main__.py
osmatching/osmatching.py
osmatching/utils.py
osmatching/validation.py
tests/test_data/__init__.py
tests/test_data/dataset_definition_cases.py
tests/test_data/dataset_definition_controls.py
opensafely_matching-1.2.3.dist-info/LICENSE
opensafely_matching-1.2.3.dist-info/METADATA
opensafely_matching-1.2.3.dist-info/WHEEL
opensafely_matching-1.2.3.dist-info/entry_points.txt
opensafely_matching-1.2.3.dist-info/top_level.txt
opensafely_matching-1.2.3.dist-info/RECORD
