Metadata-Version: 2.1
Name: opensafely-matching
Version: 1.2.3
Summary: Command line tool for matching cases to controls
Home-page: https://github.com/opensafely/matching
Author: OpenSAFELY
Author-email: tech@opensafely.org
License: GPLv3
Classifier: License :: OSI Approved :: GNU General Public License v3 (GPLv3)
Requires-Python: >=3.10
License-File: LICENSE
Requires-Dist: pandas
Requires-Dist: pyarrow
